montreal_aqi_api/__init__.py
montreal_aqi_api/api.py
montreal_aqi_api/cli.py
montreal_aqi_api/config.py
montreal_aqi_api/exceptions.py
montreal_aqi_api/pollutants.py
montreal_aqi_api/service.py
montreal_aqi_api/station.py
montreal_aqi_api/_internal/__init__.py
montreal_aqi_api/_internal/parsing.py
montreal_aqi_api/_internal/utils.py
montreal_aqi_api-0.5.0.dist-info/licenses/LICENSE
montreal_aqi_api-0.5.0.dist-info/METADATA
montreal_aqi_api-0.5.0.dist-info/WHEEL
montreal_aqi_api-0.5.0.dist-info/entry_points.txt
montreal_aqi_api-0.5.0.dist-info/top_level.txt
montreal_aqi_api-0.5.0.dist-info/RECORD
