Metadata-Version: 2.4
Name: montreal-aqi-api
Version: 0.5.0
Summary: CLI and Python API to fetch air quality index (AQI) data from the Montreal open data portal
Author-email: Normand Cyr <norm@normandcyr.com>
License: MIT
Project-URL: Homepage, https://github.com/normcyr/montreal-aqi-api
Project-URL: Repository, https://github.com/normcyr/montreal-aqi-api
Project-URL: Issues, https://github.com/normcyr/montreal-aqi-api/issues
Keywords: aqi,air-quality,montreal,open-data
Classifier: Development Status :: 4 - Beta
Classifier: Intended Audience :: Developers
Classifier: License :: OSI Approved :: MIT License
Classifier: Programming Language :: Python :: 3
Classifier: Programming Language :: Python :: 3.11
Classifier: Programming Language :: Python :: 3.12
Classifier: Programming Language :: Python :: 3.13
Classifier: Topic :: Internet :: WWW/HTTP
Classifier: Topic :: Software Development :: Libraries
Requires-Python: >=3.11
License-File: LICENSE
Requires-Dist: requests>=2.28
Provides-Extra: dev
Requires-Dist: ruff; extra == "dev"
Requires-Dist: pytest; extra == "dev"
Requires-Dist: pytest-cov; extra == "dev"
Requires-Dist: types-requests; extra == "dev"
Requires-Dist: jsonschema; extra == "dev"
Requires-Dist: types-jsonschema; extra == "dev"
Dynamic: license-file
